AUTHORS.txt
CHANGES.txt
LICENSE.txt
MANIFEST.in
README.txt
TODO.txt
bootstrap.py
buildout.cfg
setup.py
tox.ini
src/m01/__init__.py
src/m01.mongofake.egg-info/PKG-INFO
src/m01.mongofake.egg-info/SOURCES.txt
src/m01.mongofake.egg-info/dependency_links.txt
src/m01.mongofake.egg-info/not-zip-safe
src/m01.mongofake.egg-info/requires.txt
src/m01.mongofake.egg-info/top_level.txt
src/m01/mongofake/README.txt
src/m01/mongofake/__init__.py
src/m01/mongofake/testing.py
src/m01/mongofake/testing.txt
src/m01/mongofake/tests.py